arline_quantum/__init__.py
arline_quantum/gate_chain/__init__.py
arline_quantum/gate_chain/gate_chain.py
arline_quantum/gate_chain/gate_connection.py
arline_quantum/gate_sets/__init__.py
arline_quantum/gate_sets/clifford_t.py
arline_quantum/gate_sets/gate_set.py
arline_quantum/gate_sets/google.py
arline_quantum/gate_sets/ibm.py
arline_quantum/gate_sets/rigetti.py
arline_quantum/gates/__init__.py
arline_quantum/gates/ccnot.py
arline_quantum/gates/ch.py
arline_quantum/gates/cnot.py
arline_quantum/gates/crx.py
arline_quantum/gates/cry.py
arline_quantum/gates/crz.py
arline_quantum/gates/cswap.py
arline_quantum/gates/cu1.py
arline_quantum/gates/cu3.py
arline_quantum/gates/cy.py
arline_quantum/gates/cz.py
arline_quantum/gates/gate.py
arline_quantum/gates/h.py
arline_quantum/gates/identity.py
arline_quantum/gates/r.py
arline_quantum/gates/rx.py
arline_quantum/gates/ry.py
arline_quantum/gates/rz.py
arline_quantum/gates/s.py
arline_quantum/gates/swap.py
arline_quantum/gates/t.py
arline_quantum/gates/u1.py
arline_quantum/gates/u2.py
arline_quantum/gates/u3.py
arline_quantum/gates/x.py
arline_quantum/gates/xx.py
arline_quantum/gates/y.py
arline_quantum/gates/yy.py
arline_quantum/gates/z.py
arline_quantum/gates/zz.py
arline_quantum/hardware/__init__.py
arline_quantum/hardware/basic_clifford_t.py
arline_quantum/hardware/basic_google.py
arline_quantum/hardware/basic_hardware.py
arline_quantum/hardware/basic_ibm.py
arline_quantum/hardware/basic_rigetti.py
arline_quantum/hardware/hardware.py
arline_quantum/qasm_parser/__init__.py
arline_quantum/qasm_parser/exceptions.py
arline_quantum/qasm_parser/qasm.py
arline_quantum/qasm_parser/qasmlexer.py
arline_quantum/qasm_parser/qasmparser.py
arline_quantum/qasm_parser/node/__init__.py
arline_quantum/qasm_parser/node/barrier.py
arline_quantum/qasm_parser/node/binaryop.py
arline_quantum/qasm_parser/node/binaryoperator.py
arline_quantum/qasm_parser/node/cnot.py
arline_quantum/qasm_parser/node/creg.py
arline_quantum-0.1.8.dist-info/LICENSE
arline_quantum-0.1.8.dist-info/METADATA
arline_quantum-0.1.8.dist-info/WHEEL
arline_quantum-0.1.8.dist-info/top_level.txt
arline_quantum-0.1.8.dist-info/RECORD
