Metadata-Version: 2.1
Name: arline-quantum
Version: 0.1.8
Summary: Quantum Hardware Library
Home-page: https://github.com/ArlineQ/arline_quantum
Author: Turation Ltd
Author-email: info@arline.io
License: GNU Affero General Public License v3 (AGPLv3)
Platform: UNKNOWN
Classifier: Programming Language :: Python :: 3
Classifier: License :: OSI Approved :: GNU Affero General Public License v3
Classifier: Operating System :: OS Independent
Requires-Python: >=3.6
Requires-Dist: numpy (>=1.18.3)
Requires-Dist: scipy (>=1.3.1)
Requires-Dist: cirq (~=0.6.0)
Requires-Dist: qiskit (~=0.18.0)
Requires-Dist: sympy (>=1.5)
